azure/mgmt/iotcentral/__init__.py
azure/mgmt/iotcentral/_configuration.py
azure/mgmt/iotcentral/_iot_central_client.py
azure/mgmt/iotcentral/_version.py
azure/mgmt/iotcentral/aio/__init__.py
azure/mgmt/iotcentral/aio/_configuration.py
azure/mgmt/iotcentral/aio/_iot_central_client.py
azure/mgmt/iotcentral/aio/operations/__init__.py
azure/mgmt/iotcentral/aio/operations/_apps_operations.py
azure/mgmt/iotcentral/aio/operations/_operations.py
azure/mgmt/iotcentral/models/__init__.py
azure/mgmt/iotcentral/models/_iot_central_client_enums.py
azure/mgmt/iotcentral/models/_models.py
azure/mgmt/iotcentral/models/_models_py3.py
azure/mgmt/iotcentral/operations/__init__.py
azure/mgmt/iotcentral/operations/_apps_operations.py
azure/mgmt/iotcentral/operations/_operations.py
azure_mgmt_iotcentral-9.0.0.dist-info/METADATA
azure_mgmt_iotcentral-9.0.0.dist-info/WHEEL
azure_mgmt_iotcentral-9.0.0.dist-info/top_level.txt
azure_mgmt_iotcentral-9.0.0.dist-info/RECORD
